Metadata-Version: 2.1
Name: migration-toolkit
Version: 13.8.2
Summary: Flywheel Migration Toolkit
Home-page: https://gitlab.com/flywheel-io/public/migration-toolkit
License: MIT
Keywords: Flywheel,flywheel,data,migration,toolkit
Author: Flywheel
Author-email: support@flywheel.io
Requires-Python: >=3.10,<4.0
Classifier: License :: OSI Approved :: MIT License
Classifier: Programming Language :: Python :: 3
Classifier: Programming Language :: Python :: 3.10
Classifier: Programming Language :: Python :: 3.11
Classifier: Programming Language :: Python :: 3.12
Provides-Extra: all
Provides-Extra: pixel
Requires-Dist: deid (>=0.2.29) ; extra == "all" or extra == "pixel"
Requires-Dist: dotty-dict (>=1.0.0,<2.0.0)
Requires-Dist: flywheel-metadata-toolkit (>=0.1.0,<0.2.0)
Requires-Dist: fs (>=2.0.0,<3.0.0)
Requires-Dist: lxml (>=4.0.0,<5.0.0)
Requires-Dist: pandas (>=2.0.0,<3.0.0)
Requires-Dist: pathvalidate (>=2.3.0,<3.0.0)
Requires-Dist: piexif (>=1.0.0,<2.0.0)
Requires-Dist: pillow (>=10.0.0,<11.0.0)
Requires-Dist: pydicom (>=2.1.0,<3.0.0)
Requires-Dist: pypng (>=0.0.20)
Requires-Dist: python-dateutil (>=2.0.0,<3.0.0)
Requires-Dist: pytz (>=2021.1,<2022.0)
Requires-Dist: ruamel-yaml (>=0.18.0,<0.19.0)
Requires-Dist: tzlocal (>=4.1,<5.0)
Project-URL: Documentation, https://gitlab.com/flywheel-io/public/migration-toolkit
Project-URL: Repository, https://gitlab.com/flywheel-io/public/migration-toolkit
